{
    "title": "Post-Mowing Recovery",
    "subtitle": "The 15-minute window that saves you three days of limping around",
    "author": "Nate Ratcliff, LMT",
    "publisher": "Healing Hands By Nate",
    "year": 2026,
    "edition": "Between Sessions Bonus — Month 5 (May)",
    "license": "For Healing Hands By Nate Between Sessions members. Personal use only. Please don't redistribute — share the membership instead.",
    "description": "A monthly bonus protocol for the 15 minutes after you come inside that determine whether tomorrow hurts.",
    "theme": "healing-hands-warm"
}
