{
    "title": "The 30-Day Reset",
    "subtitle": "Companion Workbook — daily tracker, weekly reflections, before-and-after body inventory",
    "author": "Nate Ratcliff, LMT",
    "publisher": "Healing Hands By Nate",
    "year": 2026,
    "edition": "Standalone Program — Master Workbook",
    "license": "For Healing Hands By Nate 30-Day Reset purchasers. Personal use only. Please don't redistribute — share the program instead.",
    "description": "Use this to make the program stick. Daily tracker, weekly reflections, body inventory comparison from Day 1 to Day 30.",
    "theme": "healing-hands-warm"
}
